{
	"name": "Mana_Armored",
	"plugin-id": "Sprite",
	"sid": 370411824440666,
	"isGlobal": false,
	"instanceVariables": [
		{
			"name": "isAttacking_Melee",
			"type": "boolean",
			"desc": "",
			"sid": 564854664445253
		},
		{
			"name": "Health",
			"type": "number",
			"desc": "",
			"sid": 697362707245031
		},
		{
			"name": "AttackPower_Melee",
			"type": "number",
			"desc": "",
			"sid": 522429368967385
		},
		{
			"name": "HasMeleeWeapon",
			"type": "boolean",
			"desc": "",
			"sid": 204419798760992
		},
		{
			"name": "MaxHealth",
			"type": "number",
			"desc": "",
			"sid": 349043583637306
		}
	],
	"behaviorTypes": [
		{
			"behaviorId": "EightDir",
			"name": "8Direction",
			"sid": 690457550348923
		},
		{
			"behaviorId": "Bullet",
			"name": "Bullet",
			"sid": 304351334041988
		}
	],
	"effectTypes": [],
	"animations": {
		"items": [
			{
				"frames": [
					{
						"width": 16,
						"height": 24,
						"originX": 0.5,
						"originY": 0.5,
						"originalSource": "",
						"exportFormat": "png",
						"exportQuality": 0.8,
						"imageSpriteId": 8038931,
						"collisionPoly": {
							"points": [
								0.3475215908338479,
								0.13945760092461515,
								0.7392241365390141,
								0.14340872702966276,
								0.8123651438716726,
								0.4704561802610179,
								0.7856949937270014,
								0.9030171086079375,
								0.3050915297652147,
								0.906519292356871,
								0.2751886318604178,
								0.47413780831244257
							]
						},
						"useCollisionPoly": true,
						"duration": 1
					}
				],
				"sid": 585387158066091,
				"name": "Idle",
				"isLooping": false,
				"isPingPong": false,
				"repeatCount": 1,
				"repeatTo": 0,
				"speed": 5
			},
			{
				"frames": [
					{
						"width": 22,
						"height": 24,
						"originX": 0.36363636363636365,
						"originY": 0.5,
						"originalSource": "",
						"exportFormat": "png",
						"exportQuality": 0.8,
						"imageSpriteId": 3750379,
						"collisionPoly": {
							"points": [
								0.2527272727272727,
								0.13958333333333334,
								0.5377272727272727,
								0.14340872702966276,
								0.5909090909090909,
								0.47041666666666665,
								0.5713636363636364,
								0.9030171086079375,
								0.2218181818181818,
								0.906519292356871,
								0.2,
								0.47413780831244257
							]
						},
						"useCollisionPoly": true,
						"imagePoints": [
							{
								"name": "Image Point 1",
								"x": 0.6818181818181818,
								"y": 0.5833333333333334
							}
						],
						"duration": 1
					}
				],
				"sid": 993391530423501,
				"name": "SwingSword",
				"isLooping": false,
				"isPingPong": false,
				"repeatCount": 1,
				"repeatTo": 0,
				"speed": 5
			}
		],
		"subfolders": []
	}
}